<com.unboundid.directory.model.metrics.MetricDefinition version="3" complexity="BASIC" collectorGroup="LDAP">
  <id>
    <idString>response-time</idString>
  </id>
  <displayName>
    <MessageDescriptor.Arg0 key="INFO_RESPONSE_TIME_NAME" ordinal="-1">
      <rbBase>messages/ubid_metric</rbBase>
      <category>UBID_METRIC</category>
      <severity>INFORMATION</severity>
    </MessageDescriptor.Arg0>
    <object-array/>
  </displayName>
  <shortDisplayName>
    <MessageDescriptor.Arg0 key="INFO_RESPONSE_TIME_SHORT_NAME" ordinal="-1">
      <rbBase>messages/ubid_metric</rbBase>
      <category>UBID_METRIC</category>
      <severity>INFORMATION</severity>
    </MessageDescriptor.Arg0>
    <object-array/>
  </shortDisplayName>
  <description>
    <MessageDescriptor.Arg0 key="INFO_RESPONSE_TIME_DESCRIPTION" ordinal="-1">
      <rbBase>messages/ubid_metric</rbBase>
      <category>UBID_METRIC</category>
      <severity>INFORMATION</severity>
    </MessageDescriptor.Arg0>
    <object-array/>
  </description>
  <group>LDAP</group>
  <metricType>DiscreteValued</metricType>
  <availableStatistics>
    <com.unboundid.directory.model.metrics.Statistic>COUNT</com.unboundid.directory.model.metrics.Statistic>
    <com.unboundid.directory.model.metrics.Statistic>HISTOGRAM</com.unboundid.directory.model.metrics.Statistic>
    <com.unboundid.directory.model.metrics.Statistic>AVERAGE</com.unboundid.directory.model.metrics.Statistic>
  </availableStatistics>
  <countUnits>
    <singularName>
      <MessageDescriptor.Arg0 key="INFO_RESPTIME_SINGULAR" ordinal="-1">
        <rbBase>messages/ubid_metric</rbBase>
        <category>UBID_METRIC</category>
        <severity>INFORMATION</severity>
      </MessageDescriptor.Arg0>
      <object-array/>
    </singularName>
    <pluralName>
      <MessageDescriptor.Arg0 key="INFO_RESPTIME_PLURAL" ordinal="-1">
        <rbBase>messages/ubid_metric</rbBase>
        <category>UBID_METRIC</category>
        <severity>INFORMATION</severity>
      </MessageDescriptor.Arg0>
      <object-array/>
    </pluralName>
    <abbreviatedName>
      <MessageDescriptor.Arg0 key="INFO_RESPTIME_ABBREV" ordinal="-1">
        <rbBase>messages/ubid_metric</rbBase>
        <category>UBID_METRIC</category>
        <severity>INFORMATION</severity>
      </MessageDescriptor.Arg0>
      <object-array/>
    </abbreviatedName>
  </countUnits>
  <valueUnits>
    <singularName>
      <MessageDescriptor.Arg0 key="INFO_MSEC_SINGULAR" ordinal="-1">
        <rbBase>messages/ubid_metric</rbBase>
        <category>UBID_METRIC</category>
        <severity>INFORMATION</severity>
      </MessageDescriptor.Arg0>
      <object-array/>
    </singularName>
    <pluralName>
      <MessageDescriptor.Arg0 key="INFO_MSEC_PLURAL" ordinal="-1">
        <rbBase>messages/ubid_metric</rbBase>
        <category>UBID_METRIC</category>
        <severity>INFORMATION</severity>
      </MessageDescriptor.Arg0>
      <object-array/>
    </pluralName>
    <abbreviatedName>
      <MessageDescriptor.Arg0 key="INFO_MSEC_ABBREV" ordinal="-1">
        <rbBase>messages/ubid_metric</rbBase>
        <category>UBID_METRIC</category>
        <severity>INFORMATION</severity>
      </MessageDescriptor.Arg0>
      <object-array/>
    </abbreviatedName>
  </valueUnits>
  <dimensions>
    <com.unboundid.directory.model.metrics.Dimension>
      <id>
        <idString>application-name</idString>
      </id>
    </com.unboundid.directory.model.metrics.Dimension>
    <com.unboundid.directory.model.metrics.Dimension>
      <id>
        <idString>op-type</idString>
      </id>
      <fixedValues>
        <com.unboundid.directory.model.metrics.DimensionValue>
          <displayValue>
            <MessageDescriptor.Raw>
              <category>USER_DEFINED</category>
              <severity>INFORMATION</severity>
              <formatString>Add</formatString>
            </MessageDescriptor.Raw>
            <object-array/>
          </displayValue>
          <displayValueString>Add</displayValueString>
          <uniqueValue>add</uniqueValue>
          <dbid>0</dbid>
          <dimensionId>0</dimensionId>
        </com.unboundid.directory.model.metrics.DimensionValue>
        <com.unboundid.directory.model.metrics.DimensionValue>
          <displayValue>
            <MessageDescriptor.Raw>
              <category>USER_DEFINED</category>
              <severity>INFORMATION</severity>
              <formatString>Delete</formatString>
            </MessageDescriptor.Raw>
            <object-array/>
          </displayValue>
          <displayValueString>Delete</displayValueString>
          <uniqueValue>delete</uniqueValue>
          <dbid>0</dbid>
          <dimensionId>0</dimensionId>
        </com.unboundid.directory.model.metrics.DimensionValue>
        <com.unboundid.directory.model.metrics.DimensionValue>
          <displayValue>
            <MessageDescriptor.Raw>
              <category>USER_DEFINED</category>
              <severity>INFORMATION</severity>
              <formatString>Bind</formatString>
            </MessageDescriptor.Raw>
            <object-array/>
          </displayValue>
          <displayValueString>Bind</displayValueString>
          <uniqueValue>bind</uniqueValue>
          <dbid>0</dbid>
          <dimensionId>0</dimensionId>
        </com.unboundid.directory.model.metrics.DimensionValue>
        <com.unboundid.directory.model.metrics.DimensionValue>
          <displayValue>
            <MessageDescriptor.Raw>
              <category>USER_DEFINED</category>
              <severity>INFORMATION</severity>
              <formatString>Search</formatString>
            </MessageDescriptor.Raw>
            <object-array/>
          </displayValue>
          <displayValueString>Search</displayValueString>
          <uniqueValue>search</uniqueValue>
          <dbid>0</dbid>
          <dimensionId>0</dimensionId>
        </com.unboundid.directory.model.metrics.DimensionValue>
        <com.unboundid.directory.model.metrics.DimensionValue>
          <displayValue>
            <MessageDescriptor.Raw>
              <category>USER_DEFINED</category>
              <severity>INFORMATION</severity>
              <formatString>Compare</formatString>
            </MessageDescriptor.Raw>
            <object-array/>
          </displayValue>
          <displayValueString>Compare</displayValueString>
          <uniqueValue>compare</uniqueValue>
          <dbid>0</dbid>
          <dimensionId>0</dimensionId>
        </com.unboundid.directory.model.metrics.DimensionValue>
        <com.unboundid.directory.model.metrics.DimensionValue>
          <displayValue>
            <MessageDescriptor.Raw>
              <category>USER_DEFINED</category>
              <severity>INFORMATION</severity>
              <formatString>Modify</formatString>
            </MessageDescriptor.Raw>
            <object-array/>
          </displayValue>
          <displayValueString>Modify</displayValueString>
          <uniqueValue>modify</uniqueValue>
          <dbid>0</dbid>
          <dimensionId>0</dimensionId>
        </com.unboundid.directory.model.metrics.DimensionValue>
        <com.unboundid.directory.model.metrics.DimensionValue>
          <displayValue>
            <MessageDescriptor.Raw>
              <category>USER_DEFINED</category>
              <severity>INFORMATION</severity>
              <formatString>ModifyDN</formatString>
            </MessageDescriptor.Raw>
            <object-array/>
          </displayValue>
          <displayValueString>ModifyDN</displayValueString>
          <uniqueValue>modifydn</uniqueValue>
          <dbid>0</dbid>
          <dimensionId>0</dimensionId>
        </com.unboundid.directory.model.metrics.DimensionValue>
      </fixedValues>
    </com.unboundid.directory.model.metrics.Dimension>
  </dimensions>
</com.unboundid.directory.model.metrics.MetricDefinition>
